m_mock/m_random.py
m_mock/m_random_source.py
m_mock/mock.py
m_mock/test_case/common_utils.py
m_mock/test_case/test_basic.py
m_mock/test_case/test_date.py
m_mock/test_case/test_helper.py
m_mock/test_case/test_miscellaneous.py
m_mock/test_case/test_name.py
m_mock/test_case/test_text.py
m_mock-1.3.9.dist-info/METADATA
m_mock-1.3.9.dist-info/WHEEL
m_mock-1.3.9.dist-info/licenses/LICENSE
m_mock-1.3.9.dist-info/licenses/license.txt
m_mock-1.3.9.dist-info/RECORD
