Metadata-Version: 2.4
Name: m-mock
Version: 1.3.9
Summary: This is a tool for producing random data.
Author-email: Franciz <franciz467@163.com>
License: MIT
License-File: LICENSE
License-File: license.txt
Classifier: License :: OSI Approved :: MIT License
Classifier: Operating System :: OS Independent
Classifier: Programming Language :: Python :: 3
Requires-Python: >=3.7
Requires-Dist: python-dateutil>=2.9.0
